kaxe/__init__.py
kaxe/chart/__init__.py
kaxe/chart/bar.py
kaxe/chart/box.py
kaxe/chart/pie.py
kaxe/chart/qqplot.py
kaxe/core/__init__.py
kaxe/core/axis.py
kaxe/core/color.py
kaxe/core/draw.py
kaxe/core/fileloader.py
kaxe/core/helper.py
kaxe/core/legend.py
kaxe/core/line.py
kaxe/core/marker.py
kaxe/core/round.py
kaxe/core/shapes.py
kaxe/core/styles.py
kaxe/core/symbol.py
kaxe/core/text.py
kaxe/core/window.py
kaxe/core/d3/camera.py
kaxe/core/d3/helper.py
kaxe/core/d3/render.py
kaxe/core/d3/translator.py
kaxe/core/d3/objects/__init__.py
kaxe/core/d3/objects/color.py
kaxe/core/d3/objects/line.py
kaxe/core/d3/objects/point.py
kaxe/core/d3/objects/triangle.py
kaxe/data/__init__.py
kaxe/data/excel.py
kaxe/objects/__init__.py
kaxe/objects/function.py
kaxe/objects/legend.py
kaxe/objects/mapdata.py
kaxe/objects/point.py
kaxe/objects/d2/__init__.py
kaxe/objects/d2/arrow.py
kaxe/objects/d2/bubble.py
kaxe/objects/d2/contour.py
kaxe/objects/d2/equation.py
kaxe/objects/d2/fill.py
kaxe/objects/d2/function.py
kaxe/objects/d2/map.py
kaxe/objects/d2/parameter.py
kaxe/objects/d2/pillar.py
kaxe/objects/d2/point.py
kaxe/objects/d3/__init__.py
kaxe/objects/d3/base.py
kaxe/objects/d3/function.py
kaxe/objects/d3/mesh.py
kaxe/objects/d3/point.py
kaxe/objects/d3/potato.py
kaxe/plot/__init__.py
kaxe/plot/box.py
kaxe/plot/d3.py
kaxe/plot/double.py
kaxe/plot/empty.py
kaxe/plot/grid.py
kaxe/plot/log.py
kaxe/plot/polar.py
kaxe/plot/standard.py
kaxe/plot/themes.py
kaxe/resources/__init__.py
kaxe/resources/symbolcross.png
kaxe/resources/symboldonut.png
kaxe/resources/symbollollipop.png
kaxe/resources/symboltriangle.png
kaxe/resources/computer-modern-family/__init__.py
kaxe/resources/computer-modern-family/cmu.bright-oblique.ttf
kaxe/resources/computer-modern-family/cmu.bright-roman.ttf
kaxe/resources/computer-modern-family/cmu.bright-semibold.ttf
kaxe/resources/computer-modern-family/cmu.bright-semiboldoblique.ttf
kaxe/resources/computer-modern-family/cmu.classical-serif-italic.ttf
kaxe-1.2.7.dist-info/licenses/LICENSE
kaxe-1.2.7.dist-info/METADATA
kaxe-1.2.7.dist-info/WHEEL
kaxe-1.2.7.dist-info/top_level.txt
kaxe-1.2.7.dist-info/RECORD
