Metadata-Version: 2.4
Name: kaxe
Version: 1.2.7
Summary: A small graphing tool for functions, points, equations and more
Author-email: Valter Yde Daugberg <valteryde@hotmail.com>
Project-URL: Homepage, https://github.com/valteryde/kaxe
Project-URL: Issues, https://github.com/valteryde/kaxe/issues
Classifier: Programming Language :: Python :: 3
Classifier: License :: OSI Approved :: GNU General Public License v3 (GPLv3)
Classifier: Operating System :: OS Independent
Requires-Python: >=3.9
License-File: LICENSE
Requires-Dist: pillow
Requires-Dist: fondi
Requires-Dist: sympy
Requires-Dist: scipy
Requires-Dist: openpyxl
Requires-Dist: tqdm
Requires-Dist: numba
Dynamic: license-file
